.gitignore
LICENSE
README.md
pyproject.toml
.github/workflows/python-publish.yml
src/stcnbuf/__init__.py
src/stcnbuf/_version.py
src/stcnbuf/connected_comps.py
src/stcnbuf/improc.py
src/stcnbuf/inference_memory_bank.py
src/stcnbuf/mask_init.py
src/stcnbuf/morph.py
src/stcnbuf/myutils.py
src/stcnbuf/save_mask_video.py
src/stcnbuf/segment_video.py
src/stcnbuf/temporal_intersect.py
src/stcnbuf/videoproc.py
src/stcnbuf.egg-info/PKG-INFO
src/stcnbuf.egg-info/SOURCES.txt
src/stcnbuf.egg-info/dependency_links.txt
src/stcnbuf.egg-info/requires.txt
src/stcnbuf.egg-info/top_level.txt
src/stcnbuf/model/__init__.py
src/stcnbuf/model/cbam.py
src/stcnbuf/model/eval_network.py
src/stcnbuf/model/mod_resnet.py
src/stcnbuf/model/modules.py