Metadata-Version: 2.4
Name: stcnbuf
Version: 0.2.1
Summary: A fork of the STCN video object segmentation model.
Author-email: István Sárándi <istvan.sarandi@uni-tuebingen.de>
License-Expression: MIT
Project-URL: Homepage, https://github.com/isarandi/stcnbuf
Project-URL: Repository, https://github.com/isarandi/stcnbuf
Project-URL: Issues, https://github.com/isarandi/stcnbuf/issues
Project-URL: Author, https://istvansarandi.com
Classifier: Development Status :: 4 - Beta
Classifier: Intended Audience :: Developers
Classifier: Topic :: Software Development :: Libraries
Classifier: Programming Language :: Python
Classifier: Programming Language :: Python :: 3
Classifier: Operating System :: POSIX :: Linux
Requires-Python: >=3.6
License-File: LICENSE
Requires-Dist: torch
Requires-Dist: torchvision
Requires-Dist: numpy
Requires-Dist: opencv-python
Requires-Dist: numba
Requires-Dist: more_itertools
Requires-Dist: simplepyutils
Requires-Dist: rlemasklib
Requires-Dist: framepump
Dynamic: license-file
